{"cameraMode":{"drawMode":0,"name":"Shaded","section":"Shading Mode"},"sceneLighting":true,"audioPlay":false,"sceneViewState":{"m_AlwaysRefresh":false,"showFog":true,"showSkybox":true,"showFlares":true,"showImageEffects":true,"showParticleSystems":true,"showVisualEffectGraphs":true,"m_FxEnabled":true},"in2DMode":false,"pivot":{"x":7.015661239624023,"y":-3.237100601196289,"z":-8.958498001098633},"rotation":{"x":-0.07634364813566208,"y":-0.9064188003540039,"z":0.19607071578502656,"w":-0.36829298734664919},"size":7.072333335876465,"orthographic":false}